xbpch/__init__.py
xbpch/bpch.py
xbpch/common.py
xbpch/core.py
xbpch/grid.py
xbpch/uff.py
xbpch/variables.py
xbpch/version.py
xbpch/util/__init__.py
xbpch/util/cf.py
xbpch/util/diaginfo.py
xbpch/util/gridspec.py
xbpch-0.3.5.data/scripts/bpch_to_nc
xbpch-0.3.5.dist-info/LICENSE
xbpch-0.3.5.dist-info/METADATA
xbpch-0.3.5.dist-info/WHEEL
xbpch-0.3.5.dist-info/top_level.txt
xbpch-0.3.5.dist-info/RECORD
